google_reminder_api_wrapper/__init__.py
google_reminder_api_wrapper/api_credentials.py
google_reminder_api_wrapper/reminder_api.py
google_reminder_api_wrapper/reminder_api_base.py
google_reminder_api_wrapper/utils.py
google_reminder_api_wrapper-0.0.1.dist-info/LICENSE
google_reminder_api_wrapper-0.0.1.dist-info/METADATA
google_reminder_api_wrapper-0.0.1.dist-info/WHEEL
google_reminder_api_wrapper-0.0.1.dist-info/top_level.txt
google_reminder_api_wrapper-0.0.1.dist-info/RECORD
