Metadata-Version: 2.1
Name: google-reminder-api-wrapper
Version: 0.0.1
Summary: An unofficial API wrapper for the Google Reminder
Home-page: https://github.com/windmark/google-reminder-api-wrapper
Author: Marcus Windmark
Author-email: marcus.windmark@gmail.com
License: MIT
Platform: UNKNOWN
Classifier: Programming Language :: Python :: 3
Classifier: License :: OSI Approved :: MIT License
Classifier: Operating System :: OS Independent
